scannycheck/__init__.py
scannycheck/__main__.py
scannycheck/checker/__init__.py
scannycheck/checker/cli.py
scannycheck/checker/manager.py
scannycheck/checker/ovpn.py
scannycheck/checker/ssh.py
scannycheck/service/__init__.py
scannycheck/service/cli.py
scannycheck/service/manager.py
scannycheck/utils/__init__.py
scannycheck/utils/base_cli.py
scannycheck/utils/config.py
scannycheck/utils/logger.py
scannycheck/web/__init__.py
scannycheck/web/cli.py
scannycheck/web/server.py
scannycheck/web/utils.py
ScannyCheck-2.1.6.dist-info/LICENSE
ScannyCheck-2.1.6.dist-info/METADATA
ScannyCheck-2.1.6.dist-info/WHEEL
ScannyCheck-2.1.6.dist-info/entry_points.txt
ScannyCheck-2.1.6.dist-info/top_level.txt
ScannyCheck-2.1.6.dist-info/RECORD
