Metadata-Version: 2.1
Name: ScannyCheck
Version: 2.1.6
Summary: checkuser
Home-page: https://github.com/Interceptv/mini
Author: security virtual
Author-email: templodefogoc@gmail.com
License: MIT
Platform: UNKNOWN
Requires-Dist: python-daemon
